mcp_mlb_statsapi/__init__.py
mcp_mlb_statsapi/__main__.py
mcp_mlb_statsapi/server.py
mcp_mlb_statsapi-0.2.0.dist-info/METADATA
mcp_mlb_statsapi-0.2.0.dist-info/WHEEL
mcp_mlb_statsapi-0.2.0.dist-info/entry_points.txt
mcp_mlb_statsapi-0.2.0.dist-info/licenses/LICENSE
mcp_mlb_statsapi-0.2.0.dist-info/RECORD
