Metadata-Version: 2.4
Name: mcp_mlb_statsapi
Version: 0.2.0
Summary: Python-based MCP using the mlb-statsapi library to provide three key functionalities(Retrieve Game Results, Retrieve Game Schedule and Retrieve Specific Game Results ) related to MLB games
Author-email: PYChen <mozpizza@gmail.com>
License-Expression: MIT
License-File: LICENSE
Keywords: mcp,mlb,mlb_statsapi
Requires-Python: >=3.11
Requires-Dist: bottleneck>=1.4.2
Requires-Dist: mcp>=1.5.0
Requires-Dist: mcp[cli]>=1.5.0
Requires-Dist: mlb-statsapi>=1.8.1
Requires-Dist: pybaseball>=2.2.7
